nornir_netconf/__init__.py
nornir_netconf/plugins/connections/__init__.py
nornir_netconf/plugins/connections/netconf.py
nornir_netconf/plugins/helpers/__init__.py
nornir_netconf/plugins/helpers/general.py
nornir_netconf/plugins/helpers/models.py
nornir_netconf/plugins/helpers/rpc.py
nornir_netconf/plugins/tasks/__init__.py
nornir_netconf/plugins/tasks/capabilities/netconf_capabilities.py
nornir_netconf/plugins/tasks/editing/netconf_commit.py
nornir_netconf/plugins/tasks/editing/netconf_edit_config.py
nornir_netconf/plugins/tasks/editing/netconf_validate.py
nornir_netconf/plugins/tasks/flowmon/.gitkeep
nornir_netconf/plugins/tasks/locking/netconf_lock.py
nornir_netconf/plugins/tasks/retrieval/netconf_get.py
nornir_netconf/plugins/tasks/retrieval/netconf_get_config.py
nornir_netconf/plugins/tasks/retrieval/netconf_get_schemas.py
nornir_netconf/plugins/tasks/rpc/netconf_rpc.py
nornir_netconf-2.1.0.dist-info/LICENSE
nornir_netconf-2.1.0.dist-info/METADATA
nornir_netconf-2.1.0.dist-info/WHEEL
nornir_netconf-2.1.0.dist-info/entry_points.txt
nornir_netconf-2.1.0.dist-info/RECORD
