Metadata-Version: 2.1
Name: nornir_netconf
Version: 2.1.0
Summary: NETCONF plugin for Nornir
Home-page: https://github.com/h4ndzdatm0ld/nornir_netconf
License: Apache-2.0
Keywords: nornir,netconf,ncclient
Author: Hugo Tinoco
Author-email: hugotinoco@icloud.com
Requires-Python: >=3.9,<4.0
Classifier: License :: OSI Approved :: Apache Software License
Classifier: Programming Language :: Python :: 3
Classifier: Programming Language :: Python :: 3.9
Classifier: Programming Language :: Python :: 3.10
Classifier: Programming Language :: Python :: 3.11
Classifier: Programming Language :: Python :: 3.12
Requires-Dist: ncclient (>=0.6.9,<0.7.0)
Requires-Dist: nornir (>=3.0.0,<4.0.0)
Project-URL: Documentation, https://h4ndzdatm0ld.github.io/nornir_netconf/
Project-URL: Repository, https://github.com/h4ndzdatm0ld/nornir_netconf
